[
  {
    "id": "base",
    "alias": "",
    "armOrientation": "right",
    "coordinate": [350, 0, 0, 0, 0, 0],
    "name": "InitialPose",
    "tool": 0,
    "user": 0,
    "auxJoint": [0, 0, 0],
    "joint": [0, 32.29, 32.85, 0, 0, 0]
  },
  {
    "id": 1747986270546,
    "alias": "home",
    "armOrientation": "right",
    "coordinate": [-0.2537, 246.5262, 127.0061, 191.8286, 0, 0],
    "name": "P1",
    "tool": 0,
    "user": 0,
    "auxJoint": [0, 0, 0],
    "joint": [90.0586, -12.4526, -2.9883, 101.7705, 0, 0]
  },
  {
    "id": 1747986293689,
    "alias": "b_pick",
    "armOrientation": "right",
    "coordinate": [-0.0136, 250.702, 3.1626, 191.7766, 0, 0],
    "name": "P2",
    "tool": 0,
    "user": 0,
    "auxJoint": [0, 0, 0],
    "joint": [90.0033, 4.0428, 42.577, 101.7735, 0, 0]
  },
  {
    "id": 1747986318160,
    "alias": "pick",
    "armOrientation": "right",
    "coordinate": [1.0978, 234.97, -7.8479, 190.9414, 0, 0],
    "name": "P3",
    "tool": 0,
    "user": 0,
    "auxJoint": [0, 0, 0],
    "joint": [89.7323, 2.6039, 47.8129, 101.2091, 0, 0]
  },
  {
    "id": 1747986343299,
    "alias": "a_pick",
    "armOrientation": "right",
    "coordinate": [6.7651, 280.8871, 57.702, 189.8508, 0, 0],
    "name": "P4",
    "tool": 0,
    "user": 0,
    "auxJoint": [0, 0, 0],
    "joint": [88.6203, 2.825, 21.4816, 101.2305, 0, 0]
  },
  {
    "id": 1747986421847,
    "alias": "b_camera",
    "armOrientation": "right",
    "coordinate": [279.4312, 3.7955, 120.3717, 102.7733, 0, 0],
    "name": "P5",
    "tool": 0,
    "user": 0,
    "auxJoint": [0, 0, 0],
    "joint": [0.7786, -1.6489, 0.5099, 101.9954, 0, 0]
  },
  {
    "id": 1747987043394,
    "alias": "camer",
    "armOrientation": "right",
    "coordinate": [213.34, 11.18, 3.36, 100.48, 0, 0],
    "name": "P6",
    "tool": 0,
    "user": 0,
    "auxJoint": [0, 0, 0],
    "joint": [2.9998, -8.6501, 41.8027, 97.4802, 0, 0]
  },
  {
    "id": 1747987261761,
    "alias": "a_camera",
    "armOrientation": "right",
    "coordinate": [238.0321, 14.4039, 118.146, 100.9454, 0, 0],
    "name": "P7",
    "tool": 0,
    "user": 0,
    "auxJoint": [0, 0, 0],
    "joint": [3.4629, -15.2455, -0.7546, 97.4825, 0, 0]
  },
  {
    "id": 1747987277264,
    "alias": "b_drop",
    "armOrientation": "right",
    "coordinate": [15.7181, -234.4055, 114.7611, 11.3188, 0, 0],
    "name": "P8",
    "tool": 0,
    "user": 0,
    "auxJoint": [0, 0, 0],
    "joint": [-86.1638, -16.454, 0.0236, 97.4825, 0, 0]
  },
  {
    "id": 1747987292536,
    "alias": "drop",
    "armOrientation": "right",
    "coordinate": [29.5462, -336.4347, -37.6513, 12.5023, 0, 0],
    "name": "P9",
    "tool": 0,
    "user": 0,
    "auxJoint": [0, 0, 0],
    "joint": [-84.9811, 36.963, 45.3422, 97.4833, 0, 0]
  },
  {
    "id": 1747987304668,
    "alias": "a_drop",
    "armOrientation": "right",
    "coordinate": [30.9474, -265.5806, 114.6282, 14.1299, 0, 0],
    "name": "P10",
    "tool": 0,
    "user": 0,
    "auxJoint": [0, 0, 0],
    "joint": [-83.3535, -5.5746, 2.1431, 97.4833, 0, 0]
  }
]
